optimize.py
espminer_optim-0.0.9.dist-info/licenses/LICENSE
espminer_optim-0.0.9.dist-info/METADATA
espminer_optim-0.0.9.dist-info/WHEEL
espminer_optim-0.0.9.dist-info/entry_points.txt
espminer_optim-0.0.9.dist-info/top_level.txt
espminer_optim-0.0.9.dist-info/RECORD
