Metadata-Version: 2.4
Name: espminer-optim
Version: 0.0.9
Summary: A CLI-based tuner that runs multi-objective optimization on your ESPminer
Requires-Python: >=3.12
License-File: LICENSE
Requires-Dist: optuna>=4.2.1
Requires-Dist: optuna-dashboard>=0.18.0
Requires-Dist: pandas>=2.2.3
Requires-Dist: requests>=2.32.3
Requires-Dist: rich>=14.0.0
Dynamic: license-file
